fds/__init__.py
fds/fds_client_configuration.py
fds/fds_client_example.py
fds/fds_cmd.py
fds/fds_request.py
fds/galaxy_fds_client.py
fds/galaxy_fds_client_exception.py
fds/test_utils.py
fds/utils.py
fds/auth/__init__.py
fds/auth/common.py
fds/auth/signature/__init__.py
fds/auth/signature/signer.py
fds/model/__init__.py
fds/model/access_control_policy.py
fds/model/fds_bucket.py
fds/model/fds_object.py
fds/model/fds_object_listing.py
fds/model/fds_object_metadata.py
fds/model/fds_object_summary.py
fds/model/init_multipart_upload_result.py
fds/model/permission.py
fds/model/put_object_result.py
fds/model/quota_policy.py
fds/model/subresource.py
fds/model/upload_part_result.py
fds/model/upload_part_result_list.py
galaxy_fds_sdk_python3-0.2.dist-info/DESCRIPTION.rst
galaxy_fds_sdk_python3-0.2.dist-info/METADATA
galaxy_fds_sdk_python3-0.2.dist-info/RECORD
galaxy_fds_sdk_python3-0.2.dist-info/WHEEL
galaxy_fds_sdk_python3-0.2.dist-info/entry_points.txt
galaxy_fds_sdk_python3-0.2.dist-info/metadata.json
galaxy_fds_sdk_python3-0.2.dist-info/top_level.txt
