Metadata-Version: 2.0
Name: galaxy-fds-sdk-python3
Version: 0.2
Summary: Galaxy FDS SDK for Python3.x
Home-page: UNKNOWN
Author: http://xiangyang.li
Author-email: shawn@xiangyang.li
License: Apache License
Platform: UNKNOWN
Requires-Dist: requests (>=2.6.0)
Requires-Dist: argcomplete (>=1.4.1)
